fluent/__init__.py
fluent/asynchandler.py
fluent/asyncsender.py
fluent/event.py
fluent/handler.py
fluent/sender.py
mona_fluent_logger-0.0.6.dist-info/COPYING
mona_fluent_logger-0.0.6.dist-info/METADATA
mona_fluent_logger-0.0.6.dist-info/WHEEL
mona_fluent_logger-0.0.6.dist-info/top_level.txt
mona_fluent_logger-0.0.6.dist-info/RECORD
