Metadata-Version: 2.1
Name: mona-fluent-logger
Version: 0.0.6
Summary: A Python logging handler for Fluentd event collector
Home-page: https://github.com/itaiMona/fluent-logger-python
Author: itaiMona
Author-email: itai@monalabs.io
License: Apache License, Version 2.0
Download-URL: http://pypi.python.org/pypi/mona-fluent-logger/
Platform: UNKNOWN
Classifier: Programming Language :: Python :: 2
Classifier: Programming Language :: Python :: 2.7
Classifier: Programming Language :: Python :: 3
Classifier: Programming Language :: Python :: 3.4
Classifier: Programming Language :: Python :: 3.5
Classifier: Programming Language :: Python :: 3.6
Classifier: Programming Language :: Python :: 3.7
Classifier: Programming Language :: Python :: Implementation :: CPython
Classifier: Programming Language :: Python :: Implementation :: PyPy
Classifier: Development Status :: 5 - Production/Stable
Classifier: Topic :: System :: Logging
Classifier: Intended Audience :: Developers
Requires-Python: >=2.7,!=3.0,!=3.1,!=3.2,!=3.3,<3.9
Requires-Dist: msgpack
